numpy_ml/__init__.py
numpy_ml/bandits/__init__.py
numpy_ml/bandits/bandits.py
numpy_ml/bandits/policies.py
numpy_ml/bandits/trainer.py
numpy_ml/factorization/__init__.py
numpy_ml/factorization/factors.py
numpy_ml/factorization/metrics.py
numpy_ml/factorization/scratch.py
numpy_ml/factorization/tests.py
numpy_ml/gmm/__init__.py
numpy_ml/gmm/gmm.py
numpy_ml/hmm/__init__.py
numpy_ml/hmm/hmm.py
numpy_ml/lda/__init__.py
numpy_ml/lda/lda.py
numpy_ml/lda/lda_smoothed.py
numpy_ml/linear_models/__init__.py
numpy_ml/linear_models/lm.py
numpy_ml/neural_nets/__init__.py
numpy_ml/neural_nets/activations/__init__.py
numpy_ml/neural_nets/activations/activations.py
numpy_ml/neural_nets/initializers/__init__.py
numpy_ml/neural_nets/initializers/initializers.py
numpy_ml/neural_nets/layers/__init__.py
numpy_ml/neural_nets/layers/layers.py
numpy_ml/neural_nets/losses/__init__.py
numpy_ml/neural_nets/losses/losses.py
numpy_ml/neural_nets/models/__init__.py
numpy_ml/neural_nets/models/vae.py
numpy_ml/neural_nets/models/w2v.py
numpy_ml/neural_nets/models/wgan_gp.py
numpy_ml/neural_nets/modules/__init__.py
numpy_ml/neural_nets/modules/modules.py
numpy_ml/neural_nets/optimizers/__init__.py
numpy_ml/neural_nets/optimizers/optimizers.py
numpy_ml/neural_nets/schedulers/__init__.py
numpy_ml/neural_nets/schedulers/schedulers.py
numpy_ml/neural_nets/utils/__init__.py
numpy_ml/neural_nets/utils/utils.py
numpy_ml/neural_nets/wrappers/__init__.py
numpy_ml/neural_nets/wrappers/wrappers.py
numpy_ml/ngram/__init__.py
numpy_ml/ngram/ngram.py
numpy_ml/nonparametric/__init__.py
numpy_ml/nonparametric/gp.py
numpy_ml/nonparametric/kernel_regression.py
numpy_ml/nonparametric/knn.py
numpy_ml/preprocessing/__init__.py
numpy_ml/preprocessing/dsp.py
numpy_ml/preprocessing/general.py
numpy_ml/preprocessing/nlp.py
numpy_ml/rl_models/__init__.py
numpy_ml/rl_models/agents.py
numpy_ml/rl_models/rl_utils.py
numpy_ml/rl_models/trainer.py
numpy_ml/rl_models/tiles/__init__.py
numpy_ml/rl_models/tiles/tiles3.py
numpy_ml-0.1.2.dist-info/LICENSE
numpy_ml-0.1.2.dist-info/METADATA
numpy_ml-0.1.2.dist-info/WHEEL
numpy_ml-0.1.2.dist-info/top_level.txt
numpy_ml-0.1.2.dist-info/RECORD
