Metadata-Version: 2.1
Name: numpy-ml
Version: 0.1.2
Summary: Machine learning in NumPy
Home-page: https://github.com/ddbourgin/numpy-ml
Author: David Bourgin
Author-email: ddbourgin@gmail.com
License: GPLv3+
Project-URL: Bug Tracker, https://github.com/ddbourgin/numpy-ml/issues
Project-URL: Documentation, https://numpy-ml.readthedocs.io/en/latest/
Project-URL: Source, https://github.com/ddbourgin/numpy-ml
Platform: UNKNOWN
Classifier: Development Status :: 3 - Alpha
Classifier: Intended Audience :: Science/Research
Classifier: Intended Audience :: Developers
Classifier: Topic :: Scientific/Engineering
Classifier: License :: OSI Approved :: GNU General Public License (GPL)
Classifier: Operating System :: OS Independent
Classifier: Programming Language :: Python :: 3
Requires-Python: >=3.5
Requires-Dist: numpy
Requires-Dist: scipy
Provides-Extra: rl
Requires-Dist: gym ; extra == 'rl'
Requires-Dist: matplotlib ; extra == 'rl'
